{
  "id": "pr-51-11",
  "type": "free",
  "subject": "Limit Theorems",
  "topic": "§51 The Central Limit Theorem",
  "section": 51,
  "difficulty": 6,
  "subtopic": "Practice Problem 51.11",
  "question": "An insurance company issues 1250 vision care insurance policies. The number of claims filed by a policyholder under a vision care insurance policy during one year is a Poisson random variable with mean 2. Assume the numbers of claims filed by distinct policyholders are independent of one another. What is the approximate probability that there is a total of between 2450 and 2600 claims during a one-year period?",
  "answer": "",
  "explanation": "Answer not listed in the book's key — work it through, then check Finan.",
  "source": "Finan §51 — Practice Problem 51.11"
}